aiida_amber/__init__.py
aiida_amber/helpers.py
aiida_amber/calculations/__init__.py
aiida_amber/calculations/antechamber.py
aiida_amber/calculations/parmed.py
aiida_amber/calculations/pdb4amber.py
aiida_amber/calculations/sander.py
aiida_amber/calculations/tleap.py
aiida_amber/cli/__init__.py
aiida_amber/cli/antechamber.py
aiida_amber/cli/parmed.py
aiida_amber/cli/pdb4amber.py
aiida_amber/cli/sander.py
aiida_amber/cli/tleap.py
aiida_amber/data/__init__.py
aiida_amber/data/antechamber.py
aiida_amber/data/parmed.py
aiida_amber/data/parmed_input.py
aiida_amber/data/pdb4amber.py
aiida_amber/data/sander.py
aiida_amber/data/tleap.py
aiida_amber/data/tleap_input.py
aiida_amber/parsers/__init__.py
aiida_amber/parsers/antechamber.py
aiida_amber/parsers/parmed.py
aiida_amber/parsers/pdb4amber.py
aiida_amber/parsers/sander.py
aiida_amber/parsers/tleap.py
aiida_amber/utils/__init__.py
aiida_amber/utils/node_utils.py
aiida_amber/utils/searchprevious.py
aiida_amber-2.0.3.dist-info/entry_points.txt
aiida_amber-2.0.3.dist-info/licenses/LICENSE
aiida_amber-2.0.3.dist-info/WHEEL
aiida_amber-2.0.3.dist-info/METADATA
aiida_amber-2.0.3.dist-info/RECORD
