Metadata-Version: 2.4
Name: aiida-amber
Version: 2.0.3
Summary: AiiDA plugin that wraps amber molecular dynamics executables
Keywords: aiida,plugin,amber,aiida-amber
Author-email: Jas Kalayan <jas.kalayan@stfc.ac.uk>
Requires-Python: >=3.8
Classifier: Programming Language :: Python
Classifier: Programming Language :: Python :: 3.11
Classifier: Intended Audience :: Science/Research
Classifier: License :: OSI Approved :: MIT License
Classifier: Natural Language :: English
Classifier: Development Status :: 3 - Alpha
Classifier: Framework :: AiiDA
License-File: LICENSE
Requires-Dist: aiida-core>=2.4.0,<=2.6.3
Requires-Dist: voluptuous
Requires-Dist: MDAnalysis>=2.7.0
Requires-Dist: sphinx ; extra == "docs"
Requires-Dist: sphinx_rtd_theme ; extra == "docs"
Requires-Dist: sphinxcontrib-contentui ; extra == "docs"
Requires-Dist: sphinxcontrib-details-directive ; extra == "docs"
Requires-Dist: sphinx_copybutton ; extra == "docs"
Requires-Dist: furo ; extra == "docs"
Requires-Dist: markupsafe<2.1 ; extra == "docs"
Requires-Dist: pre-commit~=3.3 ; extra == "pre-commit"
Requires-Dist: pylint~=3.2.3 ; extra == "pre-commit"
Requires-Dist: pgtest~=1.3 ; extra == "testing"
Requires-Dist: wheel~=0.40 ; extra == "testing"
Requires-Dist: coverage[toml] ; extra == "testing"
Requires-Dist: pytest~=7.3 ; extra == "testing"
Requires-Dist: pytest-cov~=4.0 ; extra == "testing"
Requires-Dist: pytest-sugar~=0.9 ; extra == "testing"
Project-URL: Source, https://github.com/CCPBioSim/aiida-amber
Provides-Extra: docs
Provides-Extra: pre-commit
Provides-Extra: testing
